improv.py
pyImprov-0.1.1.dist-info/LICENSE
pyImprov-0.1.1.dist-info/METADATA
pyImprov-0.1.1.dist-info/WHEEL
pyImprov-0.1.1.dist-info/top_level.txt
pyImprov-0.1.1.dist-info/RECORD
