Metadata-Version: 2.1
Name: pyImprov
Version: 0.1.1
Summary: Host a Improv wifi provisioning server
Author-email: Mimoja <pyimprov@mimoja.de>
License: LGPL-2.1-or-later
Keywords: improv,wifi,provisioning,ble
Requires-Python: >=3.10
License-File: LICENSE
Requires-Dist: bless
Requires-Dist: dbus-next ; sys_platform == "linux"
